up_counter.v
module up_counter
#(
	parameter WIDTH = 32
)
(
	input 			       clk,
	input 			       reset,
	input 			       en,
	input 	               [WIDTH-1:0] count_max,
	output reg 			   clr,
	output reg	           [WIDTH-1:0] count
);
	

	always@(posedge clk)
		if(reset || clr)	count <= 0;
		else if(en) 		count <= count + 1;
		
	always@* clr = en & (count == count_max);
	
	
	
endmodule

clock.v
module clock
#(
	parameter WIDTH = 32
)

(
	input  wire					clk,
	input  wire					reset,
	input  wire				    en,
	input  wire	    [WIDTH-1:0]	count_max,
	input  wire     [WIDTH-1:0]	count_max_hrs,
	
	output wire 				clr_sec,
	output wire	    [WIDTH-1:0]	count_sec,
	output wire                 clr_min,
	output wire	    [WIDTH-1:0]	count_min,
	output wire                 clr_hrs,
	output wire     [WIDTH-1:0] count_hrs
	

);


up_counter
#(
	.WIDTH		        (WIDTH	   )	
)

up_counter_sec(
.clk           (clk             ),
.reset         (reset           ),
.en            (en              ),
.clr           (clr_sec         ),
.count_max     (count_max       ),
.count         (count_sec       )
);


up_counter
#(
	.WIDTH		        (WIDTH	   )	
)

up_counter_min(
.clk           (clk         ),
.reset         (reset       ),
.en            (clr_sec     ),
.clr           (clr_min     ),
.count_max     (count_max   ),
.count         (count_min   )
);


up_counter
#(
	.WIDTH		        (WIDTH	   )	
)


up_counter_hrs(
.clk           (clk             ),
.reset         (reset           ),
.en            (clr_min         ),
.clr           (clr_hrs         ),
.count_max     (count_max_hrs   ),
.count         (count_hrs       )
);


endmodule

tb_clock.v
module tb_clock;
parameter           WIDTH = 32;

reg			        clk;
reg 		        reset;
reg				    en;
reg	    [WIDTH-1:0]	count_max;
reg	    [WIDTH-1:0]	count_max_hrs;

wire                clr_sec;
wire    [WIDTH-1:0]	count_sec;
wire                clr_min;
wire    [WIDTH-1:0]	count_min;
wire                clr_hrs;
wire    [WIDTH-1:0] count_hrs;

clock
#(
	.WIDTH		        (WIDTH  )	
)

clock_inst(
.clk           (clk             ),
.reset         (reset           ),
.en            (en              ),
.count_max     (count_max       ),
.count_max_hrs (count_max_hrs   ),
.clr_sec       (clr_sec         ),
.count_sec     (count_sec       ),
.clr_min       (clr_min         ),
.count_min     (count_min       ),
.clr_hrs       (clr_hrs         ),
.count_hrs     (count_hrs       )
);

initial
begin
clk = 0;
forever
#5 clk = ~clk;
end


initial 
begin

    $dumpfile("wave.vcd");
	$dumpvars(0, tb_clock);
	
reset     = 0;
en        = 0;	
count_max = 32'd59;
count_max_hrs = 32'd23;

@(posedge clk)
reset <= #1 1;
@(posedge clk)
reset <= #1 0;

@(posedge clk);
#1 en = 1;

repeat(7200) @(posedge clk);
#1 en = 0;

repeat(20)@(posedge clk);
$finish;
   
	
end

endmodule

wave.vcd
$date
	Fri Feb 10 01:42:39 2023
$end
$version
	Icarus Verilog
$end
$timescale
	1s
$end
$scope module tb_clock $end
$var wire 1 ! clr_hrs $end
$var wire 1 " clr_min $end
$var wire 1 # clr_sec $end
$var wire 32 $ count_hrs [31:0] $end
$var wire 32 % count_min [31:0] $end
$var wire 32 & count_sec [31:0] $end
$var reg 1 ' clk $end
$var reg 32 ( count_max [31:0] $end
$var reg 32 ) count_max_hrs [31:0] $end
$var reg 1 * en $end
$var reg 1 + reset $end
$scope module clock_inst $end
$var wire 1 , clk $end
$var wire 1 ! clr_hrs $end
$var wire 1 " clr_min $end
$var wire 1 # clr_sec $end
$var wire 32 - count_hrs [31:0] $end
$var wire 32 . count_max [31:0] $end
$var wire 32 / count_max_hrs [31:0] $end
$var wire 32 0 count_min [31:0] $end
$var wire 32 1 count_sec [31:0] $end
$var wire 1 2 en $end
$var wire 1 3 reset $end
$scope module up_counter_sec $end
$var wire 1 , clk $end
$var wire 32 4 count_max [31:0] $end
$var wire 1 2 en $end
$var wire 1 3 reset $end
$var reg 1 5 clr $end
$var reg 32 6 count [31:0] $end
$upscope $end
$scope module up_counter_min $end
$var wire 1 , clk $end
$var wire 32 7 count_max [31:0] $end
$var wire 1 # en $end
$var wire 1 3 reset $end
$var reg 1 8 clr $end
$var reg 32 9 count [31:0] $end
$upscope $end
$scope module up_counter_hrs $end
$var wire 1 , clk $end
$var wire 32 : count_max [31:0] $end
$var wire 1 " en $end
$var wire 1 3 reset $end
$var reg 1 ; clr $end
$var reg 32 < count [31:0] $end
$upscope $end
$upscope $end
$upscope $end
$enddefinitions $end
#0
$dumpvars
bx <
0;
b10111 :
bx 9
08
b111011 7
bx 6
05
b111011 4
03
02
bx 1
bx 0
b10111 /
b111011 .
bx -
0,
0+
0*
b10111 )
b111011 (
0'
bx &
bx %
bx $
0#
0"
0!
$end
#5
1'
1,
#6
1+
13
#10
0'
0,
#15
b0 <
b0 $
b0 -
b0 9
b0 %
b0 0
b0 6
b0 &
b0 1
1'
1,
#16
0+
03
#20
0'
0,
#25
1'
1,
#26
1*
12
#30
0'
0,
#35
b1 6
b1 &
b1 1
1'
1,
#40
0'
0,
#45
b10 6
b10 &
b10 1
1'
1,
#50
0'
0,
#55
b11 6
b11 &
b11 1
1'
1,
#60
0'
0,
#65
b100 6
b100 &
b100 1
1'
1,
#70
0'
0,
#75
b101 6
b101 &
b101 1
1'
1,
#80
0'
0,
#85
b110 6
b110 &
b110 1
1'
1,
#90
0'
0,
#95
b111 6
b111 &
b111 1
1'
1,
#100
0'
0,
#105
b1000 6
b1000 &
b1000 1
1'
1,
#110
0'
0,
#115
b1001 6
b1001 &
b1001 1
1'
1,
#120
0'
0,
#125
b1010 6
b1010 &
b1010 1
1'
1,
#130
0'
0,
#135
b1011 6
b1011 &
b1011 1
1'
1,
#140
0'
0,
#145
b1100 6
b1100 &
b1100 1
1'
1,
#150
0'
0,
#155
b1101 6
b1101 &
b1101 1
1'
1,
#160
0'
0,
#165
b1110 6
b1110 &
b1110 1
1'
1,
#170
0'
0,
#175
b1111 6
b1111 &
b1111 1
1'
1,
#180
0'
0,
#185
b10000 6
b10000 &
b10000 1
1'
1,
#190
0'
0,
#195
b10001 6
b10001 &
b10001 1
1'
1,
#200
0'
0,
#205
b10010 6
b10010 &
b10010 1
1'
1,
#210
0'
0,
#215
b10011 6
b10011 &
b10011 1
1'
1,
#220
0'
0,
#225
b10100 6
b10100 &
b10100 1
1'
1,
#230
0'
0,
#235
b10101 6
b10101 &
b10101 1
1'
1,
#240
0'
0,
#245
b10110 6
b10110 &
b10110 1
1'
1,
#250
0'
0,
#255
b10111 6
b10111 &
b10111 1
1'
1,
#260
0'
0,
#265
b11000 6
b11000 &
b11000 1
1'
1,
#270
0'
0,
#275
b11001 6
b11001 &
b11001 1
1'
1,
#280
0'
0,
#285
b11010 6
b11010 &
b11010 1
1'
1,
#290
0'
0,
#295
b11011 6
b11011 &
b11011 1
1'
1,
#300
0'
0,
#305
b11100 6
b11100 &
b11100 1
1'
1,
#310
0'
0,
#315
b11101 6
b11101 &
b11101 1
1'
1,
#320
0'
0,
#325
b11110 6
b11110 &
b11110 1
1'
1,
#330
0'
0,
#335
b11111 6
b11111 &
b11111 1
1'
1,
#340
0'
0,
#345
b100000 6
b100000 &
b100000 1
1'
1,
#350
0'
0,
#355
b100001 6
b100001 &
b100001 1
1'
1,
#360
0'
0,
#365
b100010 6
b100010 &
b100010 1
1'
1,
#370
0'
0,
#375
b100011 6
b100011 &
b100011 1
1'
1,
#380
0'
0,
#385
b100100 6
b100100 &
b100100 1
1'
1,
#390
0'
0,
#395
b100101 6
b100101 &
b100101 1
1'
1,
#400
0'
0,
#405
b100110 6
b100110 &
b100110 1
1'
1,
#410
0'
0,
#415
b100111 6
b100111 &
b100111 1
1'
1,
#420
0'
0,
#425
b101000 6
b101000 &
b101000 1
1'
1,
#430
0'
0,
#435
b101001 6
b101001 &
b101001 1
1'
1,
#440
0'
0,
#445
b101010 6
b101010 &
b101010 1
1'
1,
#450
0'
0,
#455
b101011 6
b101011 &
b101011 1
1'
1,
#460
0'
0,
#465
b101100 6
b101100 &
b101100 1
1'
1,
#470
0'
0,
#475
b101101 6
b101101 &
b101101 1
1'
1,
#480
0'
0,
#485
b101110 6
b101110 &
b101110 1
1'
1,
#490
0'
0,
#495
b101111 6
b101111 &
b101111 1
1'
1,
#500
0'
0,
#505
b110000 6
b110000 &
b110000 1
1'
1,
#510
0'
0,
#515
b110001 6
b110001 &
b110001 1
1'
1,
#520
0'
0,
#525
b110010 6
b110010 &
b110010 1
1'
1,
#530
0'
0,
#535
b110011 6
b110011 &
b110011 1
1'
1,
#540
0'
0,
#545
b110100 6
b110100 &
b110100 1
1'
1,
#550
0'
0,
#555
b110101 6
b110101 &
b110101 1
1'
1,
#560
0'
0,
#565
b110110 6
b110110 &
b110110 1
1'
1,
#570
0'
0,
#575
b110111 6
b110111 &
b110111 1
1'
1,
#580
0'
0,
#585
b111000 6
b111000 &
b111000 1
1'
1,
#590
0'
0,
#595
b111001 6
b111001 &
b111001 1
1'
1,
#600
0'
0,
#605
b111010 6
b111010 &
b111010 1
1'
1,
#610
0'
0,
#615
15
1#
b111011 6
b111011 &
b111011 1
1'
1,
#620
0'
0,
#625
05
0#
b0 6
b0 &
b0 1
b1 9
b1 %
b1 0
1'
1,
#630
0'
0,
#635
b1 6
b1 &
b1 1
1'
1,
#640
0'
0,
#645
b10 6
b10 &
b10 1
1'
1,
#650
0'
0,
#655
b11 6
b11 &
b11 1
1'
1,
#660
0'
0,
#665
b100 6
b100 &
b100 1
1'
1,
#670
0'
0,
#675
b101 6
b101 &
b101 1
1'
1,
#680
0'
0,
#685
b110 6
b110 &
b110 1
1'
1,
#690
0'
0,
#695
b111 6
b111 &
b111 1
1'
1,
#700
0'
0,
#705
b1000 6
b1000 &
b1000 1
1'
1,
#710
0'
0,
#715
b1001 6
b1001 &
b1001 1
1'
1,
#720
0'
0,
#725
b1010 6
b1010 &
b1010 1
1'
1,
#730
0'
0,
#735
b1011 6
b1011 &
b1011 1
1'
1,
#740
0'
0,
#745
b1100 6
b1100 &
b1100 1
1'
1,
#750
0'
0,
#755
b1101 6
b1101 &
b1101 1
1'
1,
#760
0'
0,
#765
b1110 6
b1110 &
b1110 1
1'
1,
#770
0'
0,
#775
b1111 6
b1111 &
b1111 1
1'
1,
#780
0'
0,
#785
b10000 6
b10000 &
b10000 1
1'
1,
#790
0'
0,
#795
b10001 6
b10001 &
b10001 1
1'
1,
#800
0'
0,
#805
b10010 6
b10010 &
b10010 1
1'
1,
#810
0'
0,
#815
b10011 6
b10011 &
b10011 1
1'
1,
#820
0'
0,
#825
b10100 6
b10100 &
b10100 1
1'
1,
#830
0'
0,
#835
b10101 6
b10101 &
b10101 1
1'
1,
#840
0'
0,
#845
b10110 6
b10110 &
b10110 1
1'
1,
#850
0'
0,
#855
b10111 6
b10111 &
b10111 1
1'
1,
#860
0'
0,
#865
b11000 6
b11000 &
b11000 1
1'
1,
#870
0'
0,
#875
b11001 6
b11001 &
b11001 1
1'
1,
#880
0'
0,
#885
b11010 6
b11010 &
b11010 1
1'
1,
#890
0'
0,
#895
b11011 6
b11011 &
b11011 1
1'
1,
#900
0'
0,
#905
b11100 6
b11100 &
b11100 1
1'
1,
#910
0'
0,
#915
b11101 6
b11101 &
b11101 1
1'
1,
#920
0'
0,
#925
b11110 6
b11110 &
b11110 1
1'
1,
#930
0'
0,
#935
b11111 6
b11111 &
b11111 1
1'
1,
#940
0'
0,
#945
b100000 6
b100000 &
b100000 1
1'
1,
#950
0'
0,
#955
b100001 6
b100001 &
b100001 1
1'
1,
#960
0'
0,
#965
b100010 6
b100010 &
b100010 1
1'
1,
#970
0'
0,
#975
b100011 6
b100011 &
b100011 1
1'
1,
#980
0'
0,
#985
b100100 6
b100100 &
b100100 1
1'
1,
#990
0'
0,
#995
b100101 6
b100101 &
b100101 1
1'
1,
#1000
0'
0,
#1005
b100110 6
b100110 &
b100110 1
1'
1,
#1010
0'
0,
#1015
b100111 6
b100111 &
b100111 1
1'
1,
#1020
0'
0,
#1025
b101000 6
b101000 &
b101000 1
1'
1,
#1030
0'
0,
#1035
b101001 6
b101001 &
b101001 1
1'
1,
#1040
0'
0,
#1045
b101010 6
b101010 &
b101010 1
1'
1,
#1050
0'
0,
#1055
b101011 6
b101011 &
b101011 1
1'
1,
#1060
0'
0,
#1065
b101100 6
b101100 &
b101100 1
1'
1,
#1070
0'
0,
#1075
b101101 6
b101101 &
b101101 1
1'
1,
#1080
0'
0,
#1085
b101110 6
b101110 &
b101110 1
1'
1,
#1090
0'
0,
#1095
b101111 6
b101111 &
b101111 1
1'
1,
#1100
0'
0,
#1105
b110000 6
b110000 &
b110000 1
1'
1,
#1110
0'
0,
#1115
b110001 6
b110001 &
b110001 1
1'
1,
#1120
0'
0,
#1125
b110010 6
b110010 &
b110010 1
1'
1,
#1130
0'
0,
#1135
b110011 6
b110011 &
b110011 1
1'
1,
#1140
0'
0,
#1145
b110100 6
b110100 &
b110100 1
1'
1,
#1150
0'
0,
#1155
b110101 6
b110101 &
b110101 1
1'
1,
#1160
0'
0,
#1165
b110110 6
b110110 &
b110110 1
1'
1,
#1170
0'
0,
#1175
b110111 6
b110111 &
b110111 1
1'
1,
#1180
0'
0,
#1185
b111000 6
b111000 &
b111000 1
1'
1,
#1190
0'
0,
#1195
b111001 6
b111001 &
b111001 1
1'
1,
#1200
0'
0,
#1205
b111010 6
b111010 &
b111010 1
1'
1,
#1210
0'
0,
#1215
15
1#
b111011 6
b111011 &
b111011 1
1'
1,
#1220
0'
0,
#1225
05
0#
b0 6
b0 &
b0 1
b10 9
b10 %
b10 0
1'
1,
#1230
0'
0,
#1235
b1 6
b1 &
b1 1
1'
1,
#1240
0'
0,
#1245
b10 6
b10 &
b10 1
1'
1,
#1250
0'
0,
#1255
b11 6
b11 &
b11 1
1'
1,
#1260
0'
0,
#1265
b100 6
b100 &
b100 1
1'
1,
#1270
0'
0,
#1275
b101 6
b101 &
b101 1
1'
1,
#1280
0'
0,
#1285
b110 6
b110 &
b110 1
1'
1,
#1290
0'
0,
#1295
b111 6
b111 &
b111 1
1'
1,
#1300
0'
0,
#1305
b1000 6
b1000 &
b1000 1
1'
1,
#1310
0'
0,
#1315
b1001 6
b1001 &
b1001 1
1'
1,
#1320
0'
0,
#1325
b1010 6
b1010 &
b1010 1
1'
1,
#1330
0'
0,
#1335
b1011 6
b1011 &
b1011 1
1'
1,
#1340
0'
0,
#1345
b1100 6
b1100 &
b1100 1
1'
1,
#1350
0'
0,
#1355
b1101 6
b1101 &
b1101 1
1'
1,
#1360
0'
0,
#1365
b1110 6
b1110 &
b1110 1
1'
1,
#1370
0'
0,
#1375
b1111 6
b1111 &
b1111 1
1'
1,
#1380
0'
0,
#1385
b10000 6
b10000 &
b10000 1
1'
1,
#1390
0'
0,
#1395
b10001 6
b10001 &
b10001 1
1'
1,
#1400
0'
0,
#1405
b10010 6
b10010 &
b10010 1
1'
1,
#1410
0'
0,
#1415
b10011 6
b10011 &
b10011 1
1'
1,
#1420
0'
0,
#1425
b10100 6
b10100 &
b10100 1
1'
1,
#1430
0'
0,
#1435
b10101 6
b10101 &
b10101 1
1'
1,
#1440
0'
0,
#1445
b10110 6
b10110 &
b10110 1
1'
1,
#1450
0'
0,
#1455
b10111 6
b10111 &
b10111 1
1'
1,
#1460
0'
0,
#1465
b11000 6
b11000 &
b11000 1
1'
1,
#1470
0'
0,
#1475
b11001 6
b11001 &
b11001 1
1'
1,
#1480
0'
0,
#1485
b11010 6
b11010 &
b11010 1
1'
1,
#1490
0'
0,
#1495
b11011 6
b11011 &
b11011 1
1'
1,
#1500
0'
0,
#1505
b11100 6
b11100 &
b11100 1
1'
1,
#1510
0'
0,
#1515
b11101 6
b11101 &
b11101 1
1'
1,
#1520
0'
0,
#1525
b11110 6
b11110 &
b11110 1
1'
1,
#1530
0'
0,
#1535
b11111 6
b11111 &
b11111 1
1'
1,
#1540
0'
0,
#1545
b100000 6
b100000 &
b100000 1
1'
1,
#1550
0'
0,
#1555
b100001 6
b100001 &
b100001 1
1'
1,
#1560
0'
0,
#1565
b100010 6
b100010 &
b100010 1
1'
1,
#1570
0'
0,
#1575
b100011 6
b100011 &
b100011 1
1'
1,
#1580
0'
0,
#1585
b100100 6
b100100 &
b100100 1
1'
1,
#1590
0'
0,
#1595
b100101 6
b100101 &
b100101 1
1'
1,
#1600
0'
0,
#1605
b100110 6
b100110 &
b100110 1
1'
1,
#1610
0'
0,
#1615
b100111 6
b100111 &
b100111 1
1'
1,
#1620
0'
0,
#1625
b101000 6
b101000 &
b101000 1
1'
1,
#1630
0'
0,
#1635
b101001 6
b101001 &
b101001 1
1'
1,
#1640
0'
0,
#1645
b101010 6
b101010 &
b101010 1
1'
1,
#1650
0'
0,
#1655
b101011 6
b101011 &
b101011 1
1'
1,
#1660
0'
0,
#1665
b101100 6
b101100 &
b101100 1
1'
1,
#1670
0'
0,
#1675
b101101 6
b101101 &
b101101 1
1'
1,
#1680
0'
0,
#1685
b101110 6
b101110 &
b101110 1
1'
1,
#1690
0'
0,
#1695
b101111 6
b101111 &
b101111 1
1'
1,
#1700
0'
0,
#1705
b110000 6
b110000 &
b110000 1
1'
1,
#1710
0'
0,
#1715
b110001 6
b110001 &
b110001 1
1'
1,
#1720
0'
0,
#1725
b110010 6
b110010 &
b110010 1
1'
1,
#1730
0'
0,
#1735
b110011 6
b110011 &
b110011 1
1'
1,
#1740
0'
0,
#1745
b110100 6
b110100 &
b110100 1
1'
1,
#1750
0'
0,
#1755
b110101 6
b110101 &
b110101 1
1'
1,
#1760
0'
0,
#1765
b110110 6
b110110 &
b110110 1
1'
1,
#1770
0'
0,
#1775
b110111 6
b110111 &
b110111 1
1'
1,
#1780
0'
0,
#1785
b111000 6
b111000 &
b111000 1
1'
1,
#1790
0'
0,
#1795
b111001 6
b111001 &
b111001 1
1'
1,
#1800
0'
0,
#1805
b111010 6
b111010 &
b111010 1
1'
1,
#1810
0'
0,
#1815
15
1#
b111011 6
b111011 &
b111011 1
1'
1,
#1820
0'
0,
#1825
05
0#
b0 6
b0 &
b0 1
b11 9
b11 %
b11 0
1'
1,
#1830
0'
0,
#1835
b1 6
b1 &
b1 1
1'
1,
#1840
0'
0,
#1845
b10 6
b10 &
b10 1
1'
1,
#1850
0'
0,
#1855
b11 6
b11 &
b11 1
1'
1,
#1860
0'
0,
#1865
b100 6
b100 &
b100 1
1'
1,
#1870
0'
0,
#1875
b101 6
b101 &
b101 1
1'
1,
#1880
0'
0,
#1885
b110 6
b110 &
b110 1
1'
1,
#1890
0'
0,
#1895
b111 6
b111 &
b111 1
1'
1,
#1900
0'
0,
#1905
b1000 6
b1000 &
b1000 1
1'
1,
#1910
0'
0,
#1915
b1001 6
b1001 &
b1001 1
1'
1,
#1920
0'
0,
#1925
b1010 6
b1010 &
b1010 1
1'
1,
#1930
0'
0,
#1935
b1011 6
b1011 &
b1011 1
1'
1,
#1940
0'
0,
#1945
b1100 6
b1100 &
b1100 1
1'
1,
#1950
0'
0,
#1955
b1101 6
b1101 &
b1101 1
1'
1,
#1960
0'
0,
#1965
b1110 6
b1110 &
b1110 1
1'
1,
#1970
0'
0,
#1975
b1111 6
b1111 &
b1111 1
1'
1,
#1980
0'
0,
#1985
b10000 6
b10000 &
b10000 1
1'
1,
#1990
0'
0,
#1995
b10001 6
b10001 &
b10001 1
1'
1,
#2000
0'
0,
#2005
b10010 6
b10010 &
b10010 1
1'
1,
#2010
0'
0,
#2015
b10011 6
b10011 &
b10011 1
1'
1,
#2020
0'
0,
#2025
b10100 6
b10100 &
b10100 1
1'
1,
#2030
0'
0,
#2035
b10101 6
b10101 &
b10101 1
1'
1,
#2040
0'
0,
#2045
b10110 6
b10110 &
b10110 1
1'
1,
#2050
0'
0,
#2055
b10111 6
b10111 &
b10111 1
1'
1,
#2060
0'
0,
#2065
b11000 6
b11000 &
b11000 1
1'
1,
#2070
0'
0,
#2075
b11001 6
b11001 &
b11001 1
1'
1,
#2080
0'
0,
#2085
b11010 6
b11010 &
b11010 1
1'
1,
#2090
0'
0,
#2095
b11011 6
b11011 &
b11011 1
1'
1,
#2100
0'
0,
#2105
b11100 6
b11100 &
b11100 1
1'
1,
#2110
0'
0,
#2115
b11101 6
b11101 &
b11101 1
1'
1,
#2120
0'
0,
#2125
b11110 6
b11110 &
b11110 1
1'
1,
#2130
0'
0,
#2135
b11111 6
b11111 &
b11111 1
1'
1,
#2140
0'
0,
#2145
b100000 6
b100000 &
b100000 1
1'
1,
#2150
0'
0,
#2155
b100001 6
b100001 &
b100001 1
1'
1,
#2160
0'
0,
#2165
b100010 6
b100010 &
b100010 1
1'
1,
#2170
0'
0,
#2175
b100011 6
b100011 &
b100011 1
1'
1,
#2180
0'
0,
#2185
b100100 6
b100100 &
b100100 1
1'
1,
#2190
0'
0,
#2195
b100101 6
b100101 &
b100101 1
1'
1,
#2200
0'
0,
#2205
b100110 6
b100110 &
b100110 1
1'
1,
#2210
0'
0,
#2215
b100111 6
b100111 &
b100111 1
1'
1,
#2220
0'
0,
#2225
b101000 6
b101000 &
b101000 1
1'
1,
#2230
0'
0,
#2235
b101001 6
b101001 &
b101001 1
1'
1,
#2240
0'
0,
#2245
b101010 6
b101010 &
b101010 1
1'
1,
#2250
0'
0,
#2255
b101011 6
b101011 &
b101011 1
1'
1,
#2260
0'
0,
#2265
b101100 6
b101100 &
b101100 1
1'
1,
#2270
0'
0,
#2275
b101101 6
b101101 &
b101101 1
1'
1,
#2280
0'
0,
#2285
b101110 6
b101110 &
b101110 1
1'
1,
#2290
0'
0,
#2295
b101111 6
b101111 &
b101111 1
1'
1,
#2300
0'
0,
#2305
b110000 6
b110000 &
b110000 1
1'
1,
#2310
0'
0,
#2315
b110001 6
b110001 &
b110001 1
1'
1,
#2320
0'
0,
#2325
b110010 6
b110010 &
b110010 1
1'
1,
#2330
0'
0,
#2335
b110011 6
b110011 &
b110011 1
1'
1,
#2340
0'
0,
#2345
b110100 6
b110100 &
b110100 1
1'
1,
#2350
0'
0,
#2355
b110101 6
b110101 &
b110101 1
1'
1,
#2360
0'
0,
#2365
b110110 6
b110110 &
b110110 1
1'
1,
#2370
0'
0,
#2375
b110111 6
b110111 &
b110111 1
1'
1,
#2380
0'
0,
#2385
b111000 6
b111000 &
b111000 1
1'
1,
#2390
0'
0,
#2395
b111001 6
b111001 &
b111001 1
1'
1,
#2400
0'
0,
#2405
b111010 6
b111010 &
b111010 1
1'
1,
#2410
0'
0,
#2415
15
1#
b111011 6
b111011 &
b111011 1
1'
1,
#2420
0'
0,
#2425
05
0#
b0 6
b0 &
b0 1
b100 9
b100 %
b100 0
1'
1,
#2430
0'
0,
#2435
b1 6
b1 &
b1 1
1'
1,
#2440
0'
0,
#2445
b10 6
b10 &
b10 1
1'
1,
#2450
0'
0,
#2455
b11 6
b11 &
b11 1
1'
1,
#2460
0'
0,
#2465
b100 6
b100 &
b100 1
1'
1,
#2470
0'
0,
#2475
b101 6
b101 &
b101 1
1'
1,
#2480
0'
0,
#2485
b110 6
b110 &
b110 1
1'
1,
#2490
0'
0,
#2495
b111 6
b111 &
b111 1
1'
1,
#2500
0'
0,
#2505
b1000 6
b1000 &
b1000 1
1'
1,
#2510
0'
0,
#2515
b1001 6
b1001 &
b1001 1
1'
1,
#2520
0'
0,
#2525
b1010 6
b1010 &
b1010 1
1'
1,
#2530
0'
0,
#2535
b1011 6
b1011 &
b1011 1
1'
1,
#2540
0'
0,
#2545
b1100 6
b1100 &
b1100 1
1'
1,
#2550
0'
0,
#2555
b1101 6
b1101 &
b1101 1
1'
1,
#2560
0'
0,
#2565
b1110 6
b1110 &
b1110 1
1'
1,
#2570
0'
0,
#2575
b1111 6
b1111 &
b1111 1
1'
1,
#2580
0'
0,
#2585
b10000 6
b10000 &
b10000 1
1'
1,
#2590
0'
0,
#2595
b10001 6
b10001 &
b10001 1
1'
1,
#2600
0'
0,
#2605
b10010 6
b10010 &
b10010 1
1'
1,
#2610
0'
0,
#2615
b10011 6
b10011 &
b10011 1
1'
1,
#2620
0'
0,
#2625
b10100 6
b10100 &
b10100 1
1'
1,
#2630
0'
0,
#2635
b10101 6
b10101 &
b10101 1
1'
1,
#2640
0'
0,
#2645
b10110 6
b10110 &
b10110 1
1'
1,
#2650
0'
0,
#2655
b10111 6
b10111 &
b10111 1
1'
1,
#2660
0'
0,
#2665
b11000 6
b11000 &
b11000 1
1'
1,
#2670
0'
0,
#2675
b11001 6
b11001 &
b11001 1
1'
1,
#2680
0'
0,
#2685
b11010 6
b11010 &
b11010 1
1'
1,
#2690
0'
0,
#2695
b11011 6
b11011 &
b11011 1
1'
1,
#2700
0'
0,
#2705
b11100 6
b11100 &
b11100 1
1'
1,
#2710
0'
0,
#2715
b11101 6
b11101 &
b11101 1
1'
1,
#2720
0'
0,
#2725
b11110 6
b11110 &
b11110 1
1'
1,
#2730
0'
0,
#2735
b11111 6
b11111 &
b11111 1
1'
1,
#2740
0'
0,
#2745
b100000 6
b100000 &
b100000 1
1'
1,
#2750
0'
0,
#2755
b100001 6
b100001 &
b100001 1
1'
1,
#2760
0'
0,
#2765
b100010 6
b100010 &
b100010 1
1'
1,
#2770
0'
0,
#2775
b100011 6
b100011 &
b100011 1
1'
1,
#2780
0'
0,
#2785
b100100 6
b100100 &
b100100 1
1'
1,
#2790
0'
0,
#2795
b100101 6
b100101 &
b100101 1
1'
1,
#2800
0'
0,
#2805
b100110 6
b100110 &
b100110 1
1'
1,
#2810
0'
0,
#2815
b100111 6
b100111 &
b100111 1
1'
1,
#2820
0'
0,
#2825
b101000 6
b101000 &
b101000 1
1'
1,
#2830
0'
0,
#2835
b101001 6
b101001 &
b101001 1
1'
1,
#2840
0'
0,
#2845
b101010 6
b101010 &
b101010 1
1'
1,
#2850
0'
0,
#2855
b101011 6
b101011 &
b101011 1
1'
1,
#2860
0'
0,
#2865
b101100 6
b101100 &
b101100 1
1'
1,
#2870
0'
0,
#2875
b101101 6
b101101 &
b101101 1
1'
1,
#2880
0'
0,
#2885
b101110 6
b101110 &
b101110 1
1'
1,
#2890
0'
0,
#2895
b101111 6
b101111 &
b101111 1
1'
1,
#2900
0'
0,
#2905
b110000 6
b110000 &
b110000 1
1'
1,
#2910
0'
0,
#2915
b110001 6
b110001 &
b110001 1
1'
1,
#2920
0'
0,
#2925
b110010 6
b110010 &
b110010 1
1'
1,
#2930
0'
0,
#2935
b110011 6
b110011 &
b110011 1
1'
1,
#2940
0'
0,
#2945
b110100 6
b110100 &
b110100 1
1'
1,
#2950
0'
0,
#2955
b110101 6
b110101 &
b110101 1
1'
1,
#2960
0'
0,
#2965
b110110 6
b110110 &
b110110 1
1'
1,
#2970
0'
0,
#2975
b110111 6
b110111 &
b110111 1
1'
1,
#2980
0'
0,
#2985
b111000 6
b111000 &
b111000 1
1'
1,
#2990
0'
0,
#2995
b111001 6
b111001 &
b111001 1
1'
1,
#3000
0'
0,
#3005
b111010 6
b111010 &
b111010 1
1'
1,
#3010
0'
0,
#3015
15
1#
b111011 6
b111011 &
b111011 1
1'
1,
#3020
0'
0,
#3025
05
0#
b0 6
b0 &
b0 1
b101 9
b101 %
b101 0
1'
1,
#3030
0'
0,
#3035
b1 6
b1 &
b1 1
1'
1,
#3040
0'
0,
#3045
b10 6
b10 &
b10 1
1'
1,
#3050
0'
0,
#3055
b11 6
b11 &
b11 1
1'
1,
#3060
0'
0,
#3065
b100 6
b100 &
b100 1
1'
1,
#3070
0'
0,
#3075
b101 6
b101 &
b101 1
1'
1,
#3080
0'
0,
#3085
b110 6
b110 &
b110 1
1'
1,
#3090
0'
0,
#3095
b111 6
b111 &
b111 1
1'
1,
#3100
0'
0,
#3105
b1000 6
b1000 &
b1000 1
1'
1,
#3110
0'
0,
#3115
b1001 6
b1001 &
b1001 1
1'
1,
#3120
0'
0,
#3125
b1010 6
b1010 &
b1010 1
1'
1,
#3130
0'
0,
#3135
b1011 6
b1011 &
b1011 1
1'
1,
#3140
0'
0,
#3145
b1100 6
b1100 &
b1100 1
1'
1,
#3150
0'
0,
#3155
b1101 6
b1101 &
b1101 1
1'
1,
#3160
0'
0,
#3165
b1110 6
b1110 &
b1110 1
1'
1,
#3170
0'
0,
#3175
b1111 6
b1111 &
b1111 1
1'
1,
#3180
0'
0,
#3185
b10000 6
b10000 &
b10000 1
1'
1,
#3190
0'
0,
#3195
b10001 6
b10001 &
b10001 1
1'
1,
#3200
0'
0,
#3205
b10010 6
b10010 &
b10010 1
1'
1,
#3210
0'
0,
#3215
b10011 6
b10011 &
b10011 1
1'
1,
#3220
0'
0,
#3225
b10100 6
b10100 &
b10100 1
1'
1,
#3230
0'
0,
#3235
b10101 6
b10101 &
b10101 1
1'
1,
#3240
0'
0,
#3245
b10110 6
b10110 &
b10110 1
1'
1,
#3250
0'
0,
#3255
b10111 6
b10111 &
b10111 1
1'
1,
#3260
0'
0,
#3265
b11000 6
b11000 &
b11000 1
1'
1,
#3270
0'
0,
#3275
b11001 6
b11001 &
b11001 1
1'
1,
#3280
0'
0,
#3285
b11010 6
b11010 &
b11010 1
1'
1,
#3290
0'
0,
#3295
b11011 6
b11011 &
b11011 1
1'
1,
#3300
0'
0,
#3305
b11100 6
b11100 &
b11100 1
1'
1,
#3310
0'
0,
#3315
b11101 6
b11101 &
b11101 1
1'
1,
#3320
0'
0,
#3325
b11110 6
b11110 &
b11110 1
1'
1,
#3330
0'
0,
#3335
b11111 6
b11111 &
b11111 1
1'
1,
#3340
0'
0,
#3345
b100000 6
b100000 &
b100000 1
1'
1,
#3350
0'
0,
#3355
b100001 6
b100001 &
b100001 1
1'
1,
#3360
0'
0,
#3365
b100010 6
b100010 &
b100010 1
1'
1,
#3370
0'
0,
#3375
b100011 6
b100011 &
b100011 1
1'
1,
#3380
0'
0,
#3385
b100100 6
b100100 &
b100100 1
1'
1,
